galera/__init__.py
galera/admin.py
galera/apps.py
galera/middleware.py
galera/models.py
galera/tests.py
galera/views.py
galera/backends/__init__.py
galera/backends/readwritesplit/__init__.py
galera/backends/readwritesplit/base.py
galera/migrations/__init__.py
django_galera-1.0.7.dist-info/LICENSE
django_galera-1.0.7.dist-info/METADATA
django_galera-1.0.7.dist-info/WHEEL
django_galera-1.0.7.dist-info/top_level.txt
django_galera-1.0.7.dist-info/RECORD
